MANIFEST.in
README.rst
setup.py
bin/pyroutes-admin.py
pyroutes/__init__.py
pyroutes/dispatcher.py
pyroutes/route.py
pyroutes/settings.py
pyroutes/utils.py
pyroutes.egg-info/PKG-INFO
pyroutes.egg-info/SOURCES.txt
pyroutes.egg-info/dependency_links.txt
pyroutes.egg-info/top_level.txt
pyroutes/contrib/__init__.py
pyroutes/contrib/autoreload.py
pyroutes/default_templates/403.xml
pyroutes/default_templates/404.xml
pyroutes/default_templates/500.xml
pyroutes/default_templates/base.xml
pyroutes/default_templates/fileserver/directory_listing.xml
pyroutes/http/__init__.py
pyroutes/http/cookies.py
pyroutes/http/request.py
pyroutes/http/response.py
pyroutes/middleware/__init__.py
pyroutes/middleware/appendslash.py
pyroutes/middleware/errors.py
pyroutes/middleware/responsify.py
pyroutes/middleware/timing.py
pyroutes/template/__init__.py
pyroutes/template/xmltemplate.py