Metadata-Version: 1.1
Name: pyroutes
Version: 0.5.0
Summary: A small WSGI wrapper for creating small python web apps
Home-page: http://github.com/pyroutes/pyroutes
Author: Kristian Klette
Author-email: klette@samfundet.no
License: GPLv2
Platform: UNKNOWN
Classifier: Development Status :: 3 - Alpha
Classifier: Intended Audience :: Developers
Classifier: License :: OSI Approved :: GNU General Public License (GPL)
Classifier: Programming Language :: Python
Classifier: Programming Language :: Python :: 2
Classifier: Programming Language :: Python :: 3
Classifier: Topic :: Internet :: WWW/HTTP
Classifier: Topic :: Internet :: WWW/HTTP :: WSGI
Classifier: Topic :: Software Development :: Libraries :: Python Modules
Classifier: Operating System :: OS Independent
Requires: wsgiref
